__init__.py
media_mgr/__init__.py
media_mgr/comms_utility.py
media_mgr/exif_rename.py
media_mgr/gather.py
media_mgr/media_cfg.py
media_mgr/mover.py
media_mgr/paths_and_drives.py
media_mgr/plex_upgrade.py
media_mgr/search.py
media_mgr/server_cfg.py
media_mgr/cli/cli_comms_utility.py
media_mgr/cli/cli_exif_rename.py
media_mgr/cli/cli_gather.py
media_mgr/cli/cli_media_cfg.py
media_mgr/cli/cli_mover.py
media_mgr/cli/cli_paths_and_drives.py
media_mgr/cli/cli_plex_upgrade.py
media_mgr/cli/cli_search.py
media_mgr/cli/cli_server_cfg.py
media_mgr-0.1.15.dist-info/licenses/LICENSE
media_mgr-0.1.15.dist-info/METADATA
media_mgr-0.1.15.dist-info/WHEEL
media_mgr-0.1.15.dist-info/entry_points.txt
media_mgr-0.1.15.dist-info/top_level.txt
media_mgr-0.1.15.dist-info/RECORD
