Metadata-Version: 2.4
Name: media-mgr
Version: 0.1.15
Summary: Media file search and categorization utilities
Author-email: Ed Waldner <waldevburry@proton.me>
Maintainer-email: Ed Waldner <waldevburry@proton.me>
Project-URL: Homepage, https://github.com/ew98/media-mgr
Project-URL: Documentation, https://github.com/ew98/media-mgr/wiki/MediaMgr
Project-URL: Issues, https://github.com/ew98/media-mgr/issues
Keywords: util,utility
Classifier: Development Status :: 3 - Alpha
Classifier: Environment :: Console
Classifier: Intended Audience :: Developers
Classifier: License :: OSI Approved :: MIT License
Classifier: Natural Language :: English
Classifier: Programming Language :: Python :: 3.10
Classifier: Programming Language :: Python :: 3.11
Classifier: Programming Language :: Python :: 3.12
Classifier: Programming Language :: Python :: 3.13
Classifier: Operating System :: OS Independent
Classifier: Topic :: Utilities
Requires-Python: >=3.9
License-File: LICENSE
Requires-Dist: argcomplete
Requires-Dist: asyncssh
Requires-Dist: quickcolor
Requires-Dist: delayviewer
Requires-Dist: showexception
Requires-Dist: corecfg
Requires-Dist: exiv2
Requires-Dist: standard-imghdr
Requires-Dist: paramiko
Requires-Dist: requests
Dynamic: license-file
